<?xml version="1.0" encoding="UTF-8"?>
<iati-activities version="2.03">
 <iati-activity hierarchy="2" humanitarian="1" iati-activities:version="2.03" xml:lang="EN" xmlns:iati-activities="http://d-portal.org/xmlns/iati-activities" xmlns:xsd="http://www.w3.org/2001/XMLSchema" xmlns:xsi="http://www.w3.org/2001/XMLSchema-instance">
  <iati-identifier>XM-OCHA-CBPF-AFG-21/3481/RA3/APC/INGO/20178</iati-identifier>
  <reporting-org ref="XM-OCHA-CBPF" secondary-reporter="0" type="22">
   <narrative xml:lang="EN">United Nations Office for the Coordination of Humanitarian Affairs</narrative>
  </reporting-org>
  <title>
   <narrative xml:lang="EN">Provision of lifesaving child protection services to most vulnerable children in Herat, Badghis and Ghor provinces</narrative>
  </title>
  <description type="2">
   <narrative xml:lang="EN">The proposed project will respond to acute child protection risks by scaling up lifesaving child protection activities to prevent, mitigate and respond to abuse, neglect, exploitation, and violence faced by girls and boys, enabling equitable, inclusive and safe access to quality child protection services for children and families affected by multiple shocks that leads to deepening humanitarian needs due to existing amp recent crisis including conflict, displacement, poverty, drought and the pandemic. The proposed project will address the protection needs of the most vulnerable children and families through:1) provision of case management services to provide children with an individualized response to address their specific protection needs, using vulnerability criteria, and through referral mechanisms that enhance their access to other services, service mapping and referral pathway mechanisms developed by WCUK through existing projects 2) provision of  psychosocial support services (PSS) and Psychological First Aid (PFA) through static and mobile Child Friendly Spaces operated by trained facilitators. A case worker will be assigned to each CFS to provide additional capacity to safely identify and refer cases from the community and provide any immediate assistance 3) strengthening community-based child protection committees through training and mentoring to enable them provide support in identification and referral of CP cases in their respective communities to the service providers and to support coordinated responses to child protection needs, particularly case management needs 4) working with community-based networks to conduct awareness-raising and information sharing on critical child protection issues to enhance child protection knowledge in affected communities and respond to identified needs. These structures will help reduce child protection risks such as child labour, begging and other child protection concerns through their communication and awareness-raising activities and advice to communities and families and  5) provision of  protection assistance (cash-for-protection) for the most at-risk individuals living in vulnerable households to enable them to access services and meet basic essential needs and  respond to protection risks and reduce the risks of adopting negative coping mechanisms in the short-term.  Cases will be identified and referred to the IPA activity through WCUK&#x2019;s complementary case management and community-based child protection work. Standardised information will be collected through these referrals to ensure consistent, transparent and comprehensive targeting based on the agreed risks and vulnerability criteria and aligned with project outcomes and objectives.
 
The project will be implemented in four AHF priority districts (2 in Herat, 1 in Badghis and 1 in Ghor) over six months&#x2019; period.   The project will also be implemented using programmatic, operational and logistic capacities of ongoing projects implemented by War Child UK in three provinces to maximize effectiveness and efficiency of the proposed project.</narrative>
  </description>
  <participating-org activity-id="XM-OCHA-CBPF-AFG23-2021" ref="XM-OCHA-CBPF-AFG23" role="1" type="40">
   <narrative xml:lang="EN">Afghanistan Humanitarian Fund</narrative>
  </participating-org>
  <participating-org role="2" type="21">
   <narrative xml:lang="EN">War Child UK</narrative>
  </participating-org>
  <participating-org role="4" type="21">
   <narrative xml:lang="EN">War Child UK</narrative>
  </participating-org>
  <activity-status code="3"></activity-status>
  <activity-date iso-date="2022-01-01" type="1"></activity-date>
  <activity-date iso-date="2022-01-01" type="2"></activity-date>
  <activity-date iso-date="2022-06-30" type="3"></activity-date>
  <activity-date iso-date="2022-06-30" type="4"></activity-date>
  <contact-info>
   <organisation>
    <narrative xml:lang="EN"></narrative>
   </organisation>
   <department>
    <narrative xml:lang="EN"></narrative>
   </department>
   <person-name>
    <narrative xml:lang="EN">Abebe Jaleta</narrative>
   </person-name>
   <job-title>
    <narrative xml:lang="EN">Programme Development   Quality Advisor</narrative>
   </job-title>
   <telephone>0728895290</telephone>
   <email>AbebeJ@warchild.org.uk</email>
  </contact-info>
  <contact-info>
   <organisation>
    <narrative xml:lang="EN"></narrative>
   </organisation>
   <department>
    <narrative xml:lang="EN"></narrative>
   </department>
   <person-name>
    <narrative xml:lang="EN">Eshaq Karimi</narrative>
   </person-name>
   <job-title>
    <narrative xml:lang="EN">Programmes Manager</narrative>
   </job-title>
   <telephone>0728895252</telephone>
   <email>Eshaqk@warchild.org.uk</email>
  </contact-info>
  <contact-info>
   <organisation>
    <narrative xml:lang="EN"></narrative>
   </organisation>
   <department>
    <narrative xml:lang="EN"></narrative>
   </department>
   <person-name>
    <narrative xml:lang="EN">Wajid Khan</narrative>
   </person-name>
   <job-title>
    <narrative xml:lang="EN">Country Director</narrative>
   </job-title>
   <telephone>0703484038</telephone>
   <email>Wajidk@warchild.org.uk</email>
  </contact-info>
  <activity-scope code="4"></activity-scope>
  <recipient-country code="AF" percentage="100"></recipient-country>
  <location ref="29">
   <name>
    <narrative xml:lang="EN">Badghis</narrative>
   </name>
   <point srsName="http://www.opengis.net/def/crs/EPSG/0/4326">
    <pos>35.16713390 63.76953840</pos>
   </point>
  </location>
  <location ref="21">
   <name>
    <narrative xml:lang="EN">Ghor</narrative>
   </name>
   <point srsName="http://www.opengis.net/def/crs/EPSG/0/4326">
    <pos>34.09957760 64.90595500</pos>
   </point>
  </location>
  <location ref="30">
   <name>
    <narrative xml:lang="EN">Hirat</narrative>
   </name>
   <point srsName="http://www.opengis.net/def/crs/EPSG/0/4326">
    <pos>34.34194400 62.20305600</pos>
   </point>
  </location>
  <sector code="10" percentage="100" vocabulary="99" vocabulary-uri="https://www.humanitarianresponse.info/en/coordination/clusters">
   <narrative xml:lang="EN">Protection</narrative>
  </sector>
  <sector code="43010" percentage="100" vocabulary="1"></sector>
  <collaboration-type code="4"></collaboration-type>
  <default-flow-type code="10"></default-flow-type>
  <default-aid-type code="C01" vocabulary="1"></default-aid-type>
  <default-tied-status code="5"></default-tied-status>
  <budget status="2" type="1">
   <period-start iso-date="2022-01-01"></period-start>
   <period-end iso-date="2022-12-31"></period-end>
   <value currency="USD" value-date="2022-01-19">392304.8</value>
  </budget>
  <capital-spend percentage="0"></capital-spend>
  <transaction humanitarian="1" ref="AFG23-20178">
   <transaction-type code="2"></transaction-type>
   <transaction-date iso-date="2022-01-19"></transaction-date>
   <value currency="USD" value-date="2022-01-19">392304.8</value>
   <provider-org provider-activity-id="XM-OCHA-CBPF-AFG23-2021" ref="XM-OCHA-CBPF-AFG23" type="40">
    <narrative xml:lang="EN">Afghanistan Humanitarian Fund</narrative>
   </provider-org>
   <receiver-org>
    <narrative xml:lang="EN">War Child UK</narrative>
   </receiver-org>
  </transaction>
  <transaction humanitarian="1" ref="3305407240">
   <transaction-type code="3"></transaction-type>
   <transaction-date iso-date="2022-02-01"></transaction-date>
   <value currency="USD" value-date="2022-02-01">313843.84</value>
   <provider-org provider-activity-id="XM-OCHA-CBPF-AFG23-2021" ref="XM-OCHA-CBPF-AFG23" type="40">
    <narrative xml:lang="EN">Afghanistan Humanitarian Fund</narrative>
   </provider-org>
   <receiver-org>
    <narrative xml:lang="EN">War Child UK</narrative>
   </receiver-org>
  </transaction>
  <document-link format="APPLICATION/HTTP" url="http://pfbi.unocha.org">
   <title>
    <narrative xml:lang="EN">Afghanistan BI 2021</narrative>
   </title>
   <category code="B17"></category>
   <language code="EN"></language>
  </document-link>
  <related-activity ref="XM-OCHA-CBPF-AFG23-2021" type="1"></related-activity>
 </iati-activity>
</iati-activities>
