<?xml version="1.0" encoding="UTF-8"?>
<iati-activities version="2.03">
 <iati-activity default-currency="USD" hierarchy="1" iati-activities:version="2.03" xml:lang="EN" xmlns:iati-activities="http://d-portal.org/xmlns/iati-activities">
  <iati-identifier>XM-DAC-41123-PROJECT-102002</iati-identifier>
  <reporting-org ref="XM-DAC-41123" type="40">
   <narrative xml:lang="EN">United Nations Industrial Development Organization</narrative>
  </reporting-org>
  <title>
   <narrative xml:lang="EN">Am&#xE9;lioration de la comp&#xE9;titivit&#xE9; des entreprises ivoiriennes des secteurs d#exportation non traditionnels</narrative>
  </title>
  <description type="1">
   <narrative xml:lang="EN">Dans la perspective d&#x2019;une stabilisation politique consolid&#xE9;e, l&#x2019;UE a sign&#xE9; en f&#xE9;vrier 2010 une convention de financement de 16 millions d&#x2019;euros appuyant le Programme d&#x2019;Appui au Commerce et &#xE0; l&#x2019;Int&#xE9;gration R&#xE9;gionale (PACIR), dont l&#x2019;objectif principal est de contribuer au renforcement de la comp&#xE9;titivit&#xE9; de l&#x2019;&#xE9;conomie ivoirienne et faciliter son insertion dans l&#x2019;&#xE9;conomie r&#xE9;gionale et mondiale. Le Programme a &#xE9;t&#xE9; identifi&#xE9; entre septembre 2008 et f&#xE9;vrier 2009 par une &#xE9;quipe de trois assistants techniques de l&#x2019;UE &#xE0; la suite d&apos;une requ&#xEA;te exprim&#xE9;e par le Minist&#xE8;re de l&#x2019;Int&#xE9;gration africaine et des ivoiriens de l&#x2019;ext&#xE9;rieur en charge de la n&#xE9;gociation de l&apos;APE. L&#x2019;identification eut lieu conjointement avec le CCI, l&#x2019;ONUDI, le FMI, la CNUCED, l&#x2019;OMD, l&#x2019;AFRITAC, et les b&#xE9;n&#xE9;ficiaires. Les quatre r&#xE9;sultats escompt&#xE9;s du PACIR portent sur (1) l&#x2019;am&#xE9;lioration du cadre des affaires ; (2) le renforcement de la comp&#xE9;titivit&#xE9; des entreprises exportatrices et l&#x2019;am&#xE9;lioration du respect des normes ; (3) la facilitation des &#xE9;changes ; et (4) l&#x2019;am&#xE9;lioration des infrastructures &#xE9;conomiques.

L&#x2019;ONUDI a &#xE9;t&#xE9; identifi&#xE9;e par l&#x2019;Union Europ&#xE9;enne et les autorit&#xE9;s nationales comme l&#x2019;institution pouvant fournir une assistance ad&#xE9;quate dans le cadre de l&#x2019;axe intitul&#xE9; &#xAB; le renforcement de la comp&#xE9;titivit&#xE9; des entreprises exportatrices et l&#x2019;am&#xE9;lioration du respect des normes&#xBB;.

Le projet pr&#xE9;voit de:
- Cr&#xE9;er une capacit&#xE9; nationale pour soutenir les PME et coop&#xE9;ratives ivoiriennes dans leurs efforts d&#x2019;am&#xE9;lioration de leur comp&#xE9;titivit&#xE9;.
- R&#xE9;aliser des cas de succ&#xE8;s de consortiums d&#x2019;exportation qui puissent servir comme exemple pour d&#x2019;autres PME et coop&#xE9;ratives souhaitant am&#xE9;liorer leur comp&#xE9;titivit&#xE9;.
- Introduire un cadre institutionnel et de mesures de soutien pour les actions d&#x2019;am&#xE9;lioration de la comp&#xE9;titivit&#xE9; des entreprises par les PME et coop&#xE9;ratives ivoiriennes et leurs consortiums/groupements.
- Int&#xE9;grer dans les normes nationales les normes internationales et des pays d&#x2019;importation des produits retenus.
- Appuyer l&#x2019;accr&#xE9;ditation de laboratoires pour les tests requis sur les produits retenus.
- Formuler et amorcer un programme de restructuration et de mise &#xE0; niveau des industries ivoiriennes.</narrative>
  </description>
  <participating-org role="1">
   <narrative xml:lang="EN">C&#xF4;te d&apos;Ivoire</narrative>
  </participating-org>
  <participating-org role="1">
   <narrative xml:lang="EN">European Union</narrative>
  </participating-org>
  <participating-org role="1">
   <narrative xml:lang="EN">Regular Budget</narrative>
  </participating-org>
  <participating-org role="1">
   <narrative xml:lang="EN">Regular Programme Of Technical Cooperation</narrative>
  </participating-org>
  <participating-org activity-id="XM-DAC-41123-PROJECT-102002" ref="XM-DAC-41123" role="4" type="40">
   <narrative xml:lang="EN">United Nations Industrial Development Organization</narrative>
  </participating-org>
  <activity-status code="3"></activity-status>
  <activity-date iso-date="2011-10-26" type="1"></activity-date>
  <activity-date iso-date="2017-12-31" type="3"></activity-date>
  <recipient-country code="CI" percentage="100"></recipient-country>
  <location>
   <location-reach code="1"></location-reach>
   <location-id code="CI" vocabulary="A4"></location-id>
   <name>
    <narrative xml:lang="EN">Abidjan</narrative>
   </name>
   <point srsName="http://www.opengis.net/def/crs/EPSG/0/4326">
    <pos>5.30966 -4.01266</pos>
   </point>
  </location>
  <location>
   <location-reach code="1"></location-reach>
   <location-id code="CI" vocabulary="A4"></location-id>
   <name>
    <narrative xml:lang="EN">C&#xF4;te d&apos;Ivoire</narrative>
   </name>
   <point srsName="http://www.opengis.net/def/crs/EPSG/0/4326">
    <pos>8 -5</pos>
   </point>
  </location>
  <sector code="321" percentage="100" vocabulary="2"></sector>
  <budget>
   <period-start iso-date="2013-01-01"></period-start>
   <period-end iso-date="2013-12-31"></period-end>
   <value currency="USD" value-date="2013-01-01">1498121.01</value>
  </budget>
  <budget>
   <period-start iso-date="2014-01-01"></period-start>
   <period-end iso-date="2014-12-31"></period-end>
   <value currency="USD" value-date="2014-01-01">2530654.12</value>
  </budget>
  <budget>
   <period-start iso-date="2015-01-01"></period-start>
   <period-end iso-date="2015-12-31"></period-end>
   <value currency="USD" value-date="2015-01-01">361029.64</value>
  </budget>
  <budget>
   <period-start iso-date="2016-01-01"></period-start>
   <period-end iso-date="2016-12-31"></period-end>
   <value currency="USD" value-date="2016-01-01">48235.36</value>
  </budget>
  <budget>
   <period-start iso-date="2017-01-01"></period-start>
   <period-end iso-date="2017-12-31"></period-end>
   <value currency="USD" value-date="2017-01-01">27393.48</value>
  </budget>
  <budget>
   <period-start iso-date="2018-01-01"></period-start>
   <period-end iso-date="2018-12-31"></period-end>
   <value currency="USD" value-date="2018-01-01">-2871.64</value>
  </budget>
  <budget>
   <period-start iso-date="2019-01-01"></period-start>
   <period-end iso-date="2019-12-31"></period-end>
   <value currency="USD" value-date="2019-01-01">-2682.59</value>
  </budget>
  <transaction ref="102002-1-02-01-2013-1">
   <transaction-type code="1"></transaction-type>
   <transaction-date iso-date="2013-12-31"></transaction-date>
   <value currency="USD" value-date="2013-12-31">2243.21</value>
   <description>
    <narrative xml:lang="EN">1.1 Institutions capacity building</narrative>
   </description>
   <recipient-country code="CI"></recipient-country>
  </transaction>
  <transaction ref="102002-1-02-01-2013-4">
   <transaction-type code="4"></transaction-type>
   <transaction-date iso-date="2013-12-31"></transaction-date>
   <value currency="USD" value-date="2013-12-31">2184.94</value>
   <description>
    <narrative xml:lang="EN">1.1 Institutions capacity building</narrative>
   </description>
   <recipient-country code="CI"></recipient-country>
  </transaction>
  <transaction ref="102002-1-02-01-2014-1">
   <transaction-type code="1"></transaction-type>
   <transaction-date iso-date="2014-12-31"></transaction-date>
   <value currency="USD" value-date="2014-12-31">-3484.11</value>
   <description>
    <narrative xml:lang="EN">1.1 Institutions capacity building</narrative>
   </description>
   <recipient-country code="CI"></recipient-country>
  </transaction>
  <transaction ref="102002-1-02-01-2014-4">
   <transaction-type code="4"></transaction-type>
   <transaction-date iso-date="2014-12-31"></transaction-date>
   <value currency="USD" value-date="2014-12-31">-3336.14</value>
   <description>
    <narrative xml:lang="EN">1.1 Institutions capacity building</narrative>
   </description>
   <recipient-country code="CI"></recipient-country>
  </transaction>
  <transaction ref="102002-1-02-01-2015-1">
   <transaction-type code="1"></transaction-type>
   <transaction-date iso-date="2015-12-31"></transaction-date>
   <value currency="USD" value-date="2015-12-31">-3718.27</value>
   <description>
    <narrative xml:lang="EN">1.1 Institutions capacity building</narrative>
   </description>
   <recipient-country code="CI"></recipient-country>
  </transaction>
  <transaction ref="102002-1-02-01-2015-4">
   <transaction-type code="4"></transaction-type>
   <transaction-date iso-date="2015-12-31"></transaction-date>
   <value currency="USD" value-date="2015-12-31">-3949.46</value>
   <description>
    <narrative xml:lang="EN">1.1 Institutions capacity building</narrative>
   </description>
   <recipient-country code="CI"></recipient-country>
  </transaction>
  <transaction ref="102002-1-02-02-2013-1">
   <transaction-type code="1"></transaction-type>
   <transaction-date iso-date="2013-12-31"></transaction-date>
   <value currency="USD" value-date="2013-12-31">27110.7</value>
   <description>
    <narrative xml:lang="EN">1.2 Enterprises capacity building</narrative>
   </description>
   <recipient-country code="CI"></recipient-country>
  </transaction>
  <transaction ref="102002-1-02-02-2013-4">
   <transaction-type code="4"></transaction-type>
   <transaction-date iso-date="2013-12-31"></transaction-date>
   <value currency="USD" value-date="2013-12-31">27254.16</value>
   <description>
    <narrative xml:lang="EN">1.2 Enterprises capacity building</narrative>
   </description>
   <recipient-country code="CI"></recipient-country>
  </transaction>
  <transaction ref="102002-1-02-02-2014-1">
   <transaction-type code="1"></transaction-type>
   <transaction-date iso-date="2014-12-31"></transaction-date>
   <value currency="USD" value-date="2014-12-31">-4116.38</value>
   <description>
    <narrative xml:lang="EN">1.2 Enterprises capacity building</narrative>
   </description>
   <recipient-country code="CI"></recipient-country>
  </transaction>
  <transaction ref="102002-1-02-02-2014-4">
   <transaction-type code="4"></transaction-type>
   <transaction-date iso-date="2014-12-31"></transaction-date>
   <value currency="USD" value-date="2014-12-31">-3862.4</value>
   <description>
    <narrative xml:lang="EN">1.2 Enterprises capacity building</narrative>
   </description>
   <recipient-country code="CI"></recipient-country>
  </transaction>
  <transaction ref="102002-1-02-02-2015-1">
   <transaction-type code="1"></transaction-type>
   <transaction-date iso-date="2015-12-31"></transaction-date>
   <value currency="USD" value-date="2015-12-31">-1966.53</value>
   <description>
    <narrative xml:lang="EN">1.2 Enterprises capacity building</narrative>
   </description>
   <recipient-country code="CI"></recipient-country>
  </transaction>
  <transaction ref="102002-1-02-02-2015-4">
   <transaction-type code="4"></transaction-type>
   <transaction-date iso-date="2015-12-31"></transaction-date>
   <value currency="USD" value-date="2015-12-31">-1976.08</value>
   <description>
    <narrative xml:lang="EN">1.2 Enterprises capacity building</narrative>
   </description>
   <recipient-country code="CI"></recipient-country>
  </transaction>
  <transaction ref="102002-1-02-03-2014-1">
   <transaction-type code="1"></transaction-type>
   <transaction-date iso-date="2014-12-31"></transaction-date>
   <value currency="USD" value-date="2014-12-31">160015.6</value>
   <description>
    <narrative xml:lang="EN">1.3 Strategic positionning studies</narrative>
   </description>
   <recipient-country code="CI"></recipient-country>
  </transaction>
  <transaction ref="102002-1-02-03-2014-4">
   <transaction-type code="4"></transaction-type>
   <transaction-date iso-date="2014-12-31"></transaction-date>
   <value currency="USD" value-date="2014-12-31">153298.79</value>
   <description>
    <narrative xml:lang="EN">1.3 Strategic positionning studies</narrative>
   </description>
   <recipient-country code="CI"></recipient-country>
  </transaction>
  <transaction ref="102002-1-02-03-2015-1">
   <transaction-type code="1"></transaction-type>
   <transaction-date iso-date="2015-12-31"></transaction-date>
   <value currency="USD" value-date="2015-12-31">-807.7</value>
   <description>
    <narrative xml:lang="EN">1.3 Strategic positionning studies</narrative>
   </description>
   <recipient-country code="CI"></recipient-country>
  </transaction>
  <transaction ref="102002-1-02-03-2015-4">
   <transaction-type code="4"></transaction-type>
   <transaction-date iso-date="2015-12-31"></transaction-date>
   <value currency="USD" value-date="2015-12-31">-13611.4</value>
   <description>
    <narrative xml:lang="EN">1.3 Strategic positionning studies</narrative>
   </description>
   <recipient-country code="CI"></recipient-country>
  </transaction>
  <transaction ref="102002-1-02-04-2013-1">
   <transaction-type code="1"></transaction-type>
   <transaction-date iso-date="2013-12-31"></transaction-date>
   <value currency="USD" value-date="2013-12-31">726914.63</value>
   <description>
    <narrative xml:lang="EN">1.4 Export consortia and enterprises</narrative>
   </description>
   <recipient-country code="CI"></recipient-country>
  </transaction>
  <transaction ref="102002-1-02-04-2013-4">
   <transaction-type code="4"></transaction-type>
   <transaction-date iso-date="2013-12-31"></transaction-date>
   <value currency="USD" value-date="2013-12-31">721012.58</value>
   <description>
    <narrative xml:lang="EN">1.4 Export consortia and enterprises</narrative>
   </description>
   <recipient-country code="CI"></recipient-country>
  </transaction>
  <transaction ref="102002-1-02-04-2014-1">
   <transaction-type code="1"></transaction-type>
   <transaction-date iso-date="2014-12-31"></transaction-date>
   <value currency="USD" value-date="2014-12-31">535373.09</value>
   <description>
    <narrative xml:lang="EN">1.4 Export consortia and enterprises</narrative>
   </description>
   <recipient-country code="CI"></recipient-country>
  </transaction>
  <transaction ref="102002-1-02-04-2014-4">
   <transaction-type code="4"></transaction-type>
   <transaction-date iso-date="2014-12-31"></transaction-date>
   <value currency="USD" value-date="2014-12-31">500193.93</value>
   <description>
    <narrative xml:lang="EN">1.4 Export consortia and enterprises</narrative>
   </description>
   <recipient-country code="CI"></recipient-country>
  </transaction>
  <transaction ref="102002-1-02-04-2015-1">
   <transaction-type code="1"></transaction-type>
   <transaction-date iso-date="2015-12-31"></transaction-date>
   <value currency="USD" value-date="2015-12-31">4.97</value>
   <description>
    <narrative xml:lang="EN">1.4 Export consortia and enterprises</narrative>
   </description>
   <recipient-country code="CI"></recipient-country>
  </transaction>
  <transaction ref="102002-1-02-04-2015-4">
   <transaction-type code="4"></transaction-type>
   <transaction-date iso-date="2015-12-31"></transaction-date>
   <value currency="USD" value-date="2015-12-31">-70921.22</value>
   <description>
    <narrative xml:lang="EN">1.4 Export consortia and enterprises</narrative>
   </description>
   <recipient-country code="CI"></recipient-country>
  </transaction>
  <transaction ref="102002-1-02-04-2016-1">
   <transaction-type code="1"></transaction-type>
   <transaction-date iso-date="2016-12-31"></transaction-date>
   <value currency="USD" value-date="2016-12-31">6743.63</value>
   <description>
    <narrative xml:lang="EN">1.4 Export consortia and enterprises</narrative>
   </description>
   <recipient-country code="CI"></recipient-country>
  </transaction>
  <transaction ref="102002-1-02-04-2016-4">
   <transaction-type code="4"></transaction-type>
   <transaction-date iso-date="2016-12-31"></transaction-date>
   <value currency="USD" value-date="2016-12-31">6531.96</value>
   <description>
    <narrative xml:lang="EN">1.4 Export consortia and enterprises</narrative>
   </description>
   <recipient-country code="CI"></recipient-country>
  </transaction>
  <transaction ref="102002-1-02-04-2017-1">
   <transaction-type code="1"></transaction-type>
   <transaction-date iso-date="2017-12-31"></transaction-date>
   <value currency="USD" value-date="2017-12-31">4630.95</value>
   <description>
    <narrative xml:lang="EN">1.4 Export consortia and enterprises</narrative>
   </description>
   <recipient-country code="CI"></recipient-country>
  </transaction>
  <transaction ref="102002-1-02-04-2017-4">
   <transaction-type code="4"></transaction-type>
   <transaction-date iso-date="2017-12-31"></transaction-date>
   <value currency="USD" value-date="2017-12-31">5101.16</value>
   <description>
    <narrative xml:lang="EN">1.4 Export consortia and enterprises</narrative>
   </description>
   <recipient-country code="CI"></recipient-country>
  </transaction>
  <transaction ref="102002-1-03-01-2013-1">
   <transaction-type code="1"></transaction-type>
   <transaction-date iso-date="2013-12-31"></transaction-date>
   <value currency="USD" value-date="2013-12-31">37830.27</value>
   <description>
    <narrative xml:lang="EN">2.1 Standards integration</narrative>
   </description>
   <recipient-country code="CI"></recipient-country>
  </transaction>
  <transaction ref="102002-1-03-01-2013-4">
   <transaction-type code="4"></transaction-type>
   <transaction-date iso-date="2013-12-31"></transaction-date>
   <value currency="USD" value-date="2013-12-31">36666.63</value>
   <description>
    <narrative xml:lang="EN">2.1 Standards integration</narrative>
   </description>
   <recipient-country code="CI"></recipient-country>
  </transaction>
  <transaction ref="102002-1-03-01-2014-1">
   <transaction-type code="1"></transaction-type>
   <transaction-date iso-date="2014-12-31"></transaction-date>
   <value currency="USD" value-date="2014-12-31">60920.39</value>
   <description>
    <narrative xml:lang="EN">2.1 Standards integration</narrative>
   </description>
   <recipient-country code="CI"></recipient-country>
  </transaction>
  <transaction ref="102002-1-03-01-2014-4">
   <transaction-type code="4"></transaction-type>
   <transaction-date iso-date="2014-12-31"></transaction-date>
   <value currency="USD" value-date="2014-12-31">58575.57</value>
   <description>
    <narrative xml:lang="EN">2.1 Standards integration</narrative>
   </description>
   <recipient-country code="CI"></recipient-country>
  </transaction>
  <transaction ref="102002-1-03-01-2015-1">
   <transaction-type code="1"></transaction-type>
   <transaction-date iso-date="2015-12-31"></transaction-date>
   <value currency="USD" value-date="2015-12-31">14731.34</value>
   <description>
    <narrative xml:lang="EN">2.1 Standards integration</narrative>
   </description>
   <recipient-country code="CI"></recipient-country>
  </transaction>
  <transaction ref="102002-1-03-01-2015-4">
   <transaction-type code="4"></transaction-type>
   <transaction-date iso-date="2015-12-31"></transaction-date>
   <value currency="USD" value-date="2015-12-31">11110.37</value>
   <description>
    <narrative xml:lang="EN">2.1 Standards integration</narrative>
   </description>
   <recipient-country code="CI"></recipient-country>
  </transaction>
  <transaction ref="102002-1-03-02-2013-1">
   <transaction-type code="1"></transaction-type>
   <transaction-date iso-date="2013-12-31"></transaction-date>
   <value currency="USD" value-date="2013-12-31">0</value>
   <description>
    <narrative xml:lang="EN">2.2 Awareness building on standards</narrative>
   </description>
   <recipient-country code="CI"></recipient-country>
  </transaction>
  <transaction ref="102002-1-03-02-2013-4">
   <transaction-type code="4"></transaction-type>
   <transaction-date iso-date="2013-12-31"></transaction-date>
   <value currency="USD" value-date="2013-12-31">89.15</value>
   <description>
    <narrative xml:lang="EN">2.2 Awareness building on standards</narrative>
   </description>
   <recipient-country code="CI"></recipient-country>
  </transaction>
  <transaction ref="102002-1-03-03-2013-1">
   <transaction-type code="1"></transaction-type>
   <transaction-date iso-date="2013-12-31"></transaction-date>
   <value currency="USD" value-date="2013-12-31">0.01</value>
   <description>
    <narrative xml:lang="EN">2.3 Product certification feasibility</narrative>
   </description>
   <recipient-country code="CI"></recipient-country>
  </transaction>
  <transaction ref="102002-1-03-03-2013-4">
   <transaction-type code="4"></transaction-type>
   <transaction-date iso-date="2013-12-31"></transaction-date>
   <value currency="USD" value-date="2013-12-31">104.01</value>
   <description>
    <narrative xml:lang="EN">2.3 Product certification feasibility</narrative>
   </description>
   <recipient-country code="CI"></recipient-country>
  </transaction>
  <transaction ref="102002-1-04-01-2013-1">
   <transaction-type code="1"></transaction-type>
   <transaction-date iso-date="2013-12-31"></transaction-date>
   <value currency="USD" value-date="2013-12-31">227650.48</value>
   <description>
    <narrative xml:lang="EN">3.1 Technical assistance on quality</narrative>
   </description>
   <recipient-country code="CI"></recipient-country>
  </transaction>
  <transaction ref="102002-1-04-01-2013-4">
   <transaction-type code="4"></transaction-type>
   <transaction-date iso-date="2013-12-31"></transaction-date>
   <value currency="USD" value-date="2013-12-31">226719.94</value>
   <description>
    <narrative xml:lang="EN">3.1 Technical assistance on quality</narrative>
   </description>
   <recipient-country code="CI"></recipient-country>
  </transaction>
  <transaction ref="102002-1-04-01-2014-1">
   <transaction-type code="1"></transaction-type>
   <transaction-date iso-date="2014-12-31"></transaction-date>
   <value currency="USD" value-date="2014-12-31">461928.19</value>
   <description>
    <narrative xml:lang="EN">3.1 Technical assistance on quality</narrative>
   </description>
   <recipient-country code="CI"></recipient-country>
  </transaction>
  <transaction ref="102002-1-04-01-2014-4">
   <transaction-type code="4"></transaction-type>
   <transaction-date iso-date="2014-12-31"></transaction-date>
   <value currency="USD" value-date="2014-12-31">448896.1</value>
   <description>
    <narrative xml:lang="EN">3.1 Technical assistance on quality</narrative>
   </description>
   <recipient-country code="CI"></recipient-country>
  </transaction>
  <transaction ref="102002-1-04-01-2015-1">
   <transaction-type code="1"></transaction-type>
   <transaction-date iso-date="2015-12-31"></transaction-date>
   <value currency="USD" value-date="2015-12-31">56504.86</value>
   <description>
    <narrative xml:lang="EN">3.1 Technical assistance on quality</narrative>
   </description>
   <recipient-country code="CI"></recipient-country>
  </transaction>
  <transaction ref="102002-1-04-01-2015-4">
   <transaction-type code="4"></transaction-type>
   <transaction-date iso-date="2015-12-31"></transaction-date>
   <value currency="USD" value-date="2015-12-31">1604.88</value>
   <description>
    <narrative xml:lang="EN">3.1 Technical assistance on quality</narrative>
   </description>
   <recipient-country code="CI"></recipient-country>
  </transaction>
  <transaction ref="102002-1-04-01-2016-1">
   <transaction-type code="1"></transaction-type>
   <transaction-date iso-date="2016-12-31"></transaction-date>
   <value currency="USD" value-date="2016-12-31">7628.46</value>
   <description>
    <narrative xml:lang="EN">3.1 Technical assistance on quality</narrative>
   </description>
   <recipient-country code="CI"></recipient-country>
  </transaction>
  <transaction ref="102002-1-04-01-2016-4">
   <transaction-type code="4"></transaction-type>
   <transaction-date iso-date="2016-12-31"></transaction-date>
   <value currency="USD" value-date="2016-12-31">7357.05</value>
   <description>
    <narrative xml:lang="EN">3.1 Technical assistance on quality</narrative>
   </description>
   <recipient-country code="CI"></recipient-country>
  </transaction>
  <transaction ref="102002-1-04-01-2017-1">
   <transaction-type code="1"></transaction-type>
   <transaction-date iso-date="2017-12-31"></transaction-date>
   <value currency="USD" value-date="2017-12-31">8814.56</value>
   <description>
    <narrative xml:lang="EN">3.1 Technical assistance on quality</narrative>
   </description>
   <recipient-country code="CI"></recipient-country>
  </transaction>
  <transaction ref="102002-1-04-01-2017-4">
   <transaction-type code="4"></transaction-type>
   <transaction-date iso-date="2017-12-31"></transaction-date>
   <value currency="USD" value-date="2017-12-31">9097.4</value>
   <description>
    <narrative xml:lang="EN">3.1 Technical assistance on quality</narrative>
   </description>
   <recipient-country code="CI"></recipient-country>
  </transaction>
  <transaction ref="102002-1-04-01-2018-1">
   <transaction-type code="1"></transaction-type>
   <transaction-date iso-date="2018-12-31"></transaction-date>
   <value currency="USD" value-date="2018-12-31">-0.01</value>
   <description>
    <narrative xml:lang="EN">3.1 Technical assistance on quality</narrative>
   </description>
   <recipient-country code="CI"></recipient-country>
  </transaction>
  <transaction ref="102002-1-04-01-2018-4">
   <transaction-type code="4"></transaction-type>
   <transaction-date iso-date="2018-12-31"></transaction-date>
   <value currency="USD" value-date="2018-12-31">-0.01</value>
   <description>
    <narrative xml:lang="EN">3.1 Technical assistance on quality</narrative>
   </description>
   <recipient-country code="CI"></recipient-country>
  </transaction>
  <transaction ref="102002-1-04-01-2019-1">
   <transaction-type code="1"></transaction-type>
   <transaction-date iso-date="2019-12-31"></transaction-date>
   <value currency="USD" value-date="2019-12-31">-2682.59</value>
   <description>
    <narrative xml:lang="EN">3.1 Technical assistance on quality</narrative>
   </description>
   <recipient-country code="CI"></recipient-country>
  </transaction>
  <transaction ref="102002-1-04-01-2019-4">
   <transaction-type code="4"></transaction-type>
   <transaction-date iso-date="2019-12-31"></transaction-date>
   <value currency="USD" value-date="2019-12-31">-2619.79</value>
   <description>
    <narrative xml:lang="EN">3.1 Technical assistance on quality</narrative>
   </description>
   <recipient-country code="CI"></recipient-country>
  </transaction>
  <transaction ref="102002-1-05-01-2013-1">
   <transaction-type code="1"></transaction-type>
   <transaction-date iso-date="2013-12-31"></transaction-date>
   <value currency="USD" value-date="2013-12-31">-519.57</value>
   <description>
    <narrative xml:lang="EN">4.1 Programme formulation</narrative>
   </description>
   <recipient-country code="CI"></recipient-country>
  </transaction>
  <transaction ref="102002-1-05-01-2013-4">
   <transaction-type code="4"></transaction-type>
   <transaction-date iso-date="2013-12-31"></transaction-date>
   <value currency="USD" value-date="2013-12-31">-30.39</value>
   <description>
    <narrative xml:lang="EN">4.1 Programme formulation</narrative>
   </description>
   <recipient-country code="CI"></recipient-country>
  </transaction>
  <transaction ref="102002-1-05-01-2014-1">
   <transaction-type code="1"></transaction-type>
   <transaction-date iso-date="2014-12-31"></transaction-date>
   <value currency="USD" value-date="2014-12-31">-593.8</value>
   <description>
    <narrative xml:lang="EN">4.1 Programme formulation</narrative>
   </description>
   <recipient-country code="CI"></recipient-country>
  </transaction>
  <transaction ref="102002-1-05-01-2014-4">
   <transaction-type code="4"></transaction-type>
   <transaction-date iso-date="2014-12-31"></transaction-date>
   <value currency="USD" value-date="2014-12-31">-535.44</value>
   <description>
    <narrative xml:lang="EN">4.1 Programme formulation</narrative>
   </description>
   <recipient-country code="CI"></recipient-country>
  </transaction>
  <transaction ref="102002-1-05-03-2013-1">
   <transaction-type code="1"></transaction-type>
   <transaction-date iso-date="2013-12-31"></transaction-date>
   <value currency="USD" value-date="2013-12-31">68810.68</value>
   <description>
    <narrative xml:lang="EN">4.3 Programme pilot implementation</narrative>
   </description>
   <recipient-country code="CI"></recipient-country>
  </transaction>
  <transaction ref="102002-1-05-03-2013-4">
   <transaction-type code="4"></transaction-type>
   <transaction-date iso-date="2013-12-31"></transaction-date>
   <value currency="USD" value-date="2013-12-31">69307.62</value>
   <description>
    <narrative xml:lang="EN">4.3 Programme pilot implementation</narrative>
   </description>
   <recipient-country code="CI"></recipient-country>
  </transaction>
  <transaction ref="102002-1-05-03-2014-1">
   <transaction-type code="1"></transaction-type>
   <transaction-date iso-date="2014-12-31"></transaction-date>
   <value currency="USD" value-date="2014-12-31">880805.24</value>
   <description>
    <narrative xml:lang="EN">4.3 Programme pilot implementation</narrative>
   </description>
   <recipient-country code="CI"></recipient-country>
  </transaction>
  <transaction ref="102002-1-05-03-2014-4">
   <transaction-type code="4"></transaction-type>
   <transaction-date iso-date="2014-12-31"></transaction-date>
   <value currency="USD" value-date="2014-12-31">839140.14</value>
   <description>
    <narrative xml:lang="EN">4.3 Programme pilot implementation</narrative>
   </description>
   <recipient-country code="CI"></recipient-country>
  </transaction>
  <transaction ref="102002-1-05-03-2015-1">
   <transaction-type code="1"></transaction-type>
   <transaction-date iso-date="2015-12-31"></transaction-date>
   <value currency="USD" value-date="2015-12-31">218799.88</value>
   <description>
    <narrative xml:lang="EN">4.3 Programme pilot implementation</narrative>
   </description>
   <recipient-country code="CI"></recipient-country>
  </transaction>
  <transaction ref="102002-1-05-03-2015-4">
   <transaction-type code="4"></transaction-type>
   <transaction-date iso-date="2015-12-31"></transaction-date>
   <value currency="USD" value-date="2015-12-31">186821.96</value>
   <description>
    <narrative xml:lang="EN">4.3 Programme pilot implementation</narrative>
   </description>
   <recipient-country code="CI"></recipient-country>
  </transaction>
  <transaction ref="102002-1-05-03-2016-1">
   <transaction-type code="1"></transaction-type>
   <transaction-date iso-date="2016-12-31"></transaction-date>
   <value currency="USD" value-date="2016-12-31">31973.63</value>
   <description>
    <narrative xml:lang="EN">4.3 Programme pilot implementation</narrative>
   </description>
   <recipient-country code="CI"></recipient-country>
  </transaction>
  <transaction ref="102002-1-05-03-2016-4">
   <transaction-type code="4"></transaction-type>
   <transaction-date iso-date="2016-12-31"></transaction-date>
   <value currency="USD" value-date="2016-12-31">31397</value>
   <description>
    <narrative xml:lang="EN">4.3 Programme pilot implementation</narrative>
   </description>
   <recipient-country code="CI"></recipient-country>
  </transaction>
  <transaction ref="102002-1-05-03-2017-1">
   <transaction-type code="1"></transaction-type>
   <transaction-date iso-date="2017-12-31"></transaction-date>
   <value currency="USD" value-date="2017-12-31">13947.04</value>
   <description>
    <narrative xml:lang="EN">4.3 Programme pilot implementation</narrative>
   </description>
   <recipient-country code="CI"></recipient-country>
  </transaction>
  <transaction ref="102002-1-05-03-2017-4">
   <transaction-type code="4"></transaction-type>
   <transaction-date iso-date="2017-12-31"></transaction-date>
   <value currency="USD" value-date="2017-12-31">15312.7</value>
   <description>
    <narrative xml:lang="EN">4.3 Programme pilot implementation</narrative>
   </description>
   <recipient-country code="CI"></recipient-country>
  </transaction>
  <transaction ref="102002-1-05-03-2018-1">
   <transaction-type code="1"></transaction-type>
   <transaction-date iso-date="2018-12-31"></transaction-date>
   <value currency="USD" value-date="2018-12-31">-2790.29</value>
   <description>
    <narrative xml:lang="EN">4.3 Programme pilot implementation</narrative>
   </description>
   <recipient-country code="CI"></recipient-country>
  </transaction>
  <transaction ref="102002-1-05-03-2018-4">
   <transaction-type code="4"></transaction-type>
   <transaction-date iso-date="2018-12-31"></transaction-date>
   <value currency="USD" value-date="2018-12-31">-2505.07</value>
   <description>
    <narrative xml:lang="EN">4.3 Programme pilot implementation</narrative>
   </description>
   <recipient-country code="CI"></recipient-country>
  </transaction>
  <transaction ref="102002-1-51-01-2013-1">
   <transaction-type code="1"></transaction-type>
   <transaction-date iso-date="2013-12-31"></transaction-date>
   <value currency="USD" value-date="2013-12-31">387407.11</value>
   <description>
    <narrative xml:lang="EN">5.1 Project Coordination BIT</narrative>
   </description>
   <recipient-country code="CI"></recipient-country>
  </transaction>
  <transaction ref="102002-1-51-01-2013-4">
   <transaction-type code="4"></transaction-type>
   <transaction-date iso-date="2013-12-31"></transaction-date>
   <value currency="USD" value-date="2013-12-31">393132.1</value>
   <description>
    <narrative xml:lang="EN">5.1 Project Coordination BIT</narrative>
   </description>
   <recipient-country code="CI"></recipient-country>
  </transaction>
  <transaction ref="102002-1-51-01-2014-1">
   <transaction-type code="1"></transaction-type>
   <transaction-date iso-date="2014-12-31"></transaction-date>
   <value currency="USD" value-date="2014-12-31">356235.99</value>
   <description>
    <narrative xml:lang="EN">5.1 Project Coordination BIT</narrative>
   </description>
   <recipient-country code="CI"></recipient-country>
  </transaction>
  <transaction ref="102002-1-51-01-2014-4">
   <transaction-type code="4"></transaction-type>
   <transaction-date iso-date="2014-12-31"></transaction-date>
   <value currency="USD" value-date="2014-12-31">346953.51</value>
   <description>
    <narrative xml:lang="EN">5.1 Project Coordination BIT</narrative>
   </description>
   <recipient-country code="CI"></recipient-country>
  </transaction>
  <transaction ref="102002-1-51-01-2015-1">
   <transaction-type code="1"></transaction-type>
   <transaction-date iso-date="2015-12-31"></transaction-date>
   <value currency="USD" value-date="2015-12-31">70035.08</value>
   <description>
    <narrative xml:lang="EN">5.1 Project Coordination BIT</narrative>
   </description>
   <recipient-country code="CI"></recipient-country>
  </transaction>
  <transaction ref="102002-1-51-01-2015-4">
   <transaction-type code="4"></transaction-type>
   <transaction-date iso-date="2015-12-31"></transaction-date>
   <value currency="USD" value-date="2015-12-31">62583.84</value>
   <description>
    <narrative xml:lang="EN">5.1 Project Coordination BIT</narrative>
   </description>
   <recipient-country code="CI"></recipient-country>
  </transaction>
  <transaction ref="102002-1-51-01-2016-1">
   <transaction-type code="1"></transaction-type>
   <transaction-date iso-date="2016-12-31"></transaction-date>
   <value currency="USD" value-date="2016-12-31">1889.64</value>
   <description>
    <narrative xml:lang="EN">5.1 Project Coordination BIT</narrative>
   </description>
   <recipient-country code="CI"></recipient-country>
  </transaction>
  <transaction ref="102002-1-51-01-2016-4">
   <transaction-type code="4"></transaction-type>
   <transaction-date iso-date="2016-12-31"></transaction-date>
   <value currency="USD" value-date="2016-12-31">1892.32</value>
   <description>
    <narrative xml:lang="EN">5.1 Project Coordination BIT</narrative>
   </description>
   <recipient-country code="CI"></recipient-country>
  </transaction>
  <transaction ref="102002-1-51-01-2017-1">
   <transaction-type code="1"></transaction-type>
   <transaction-date iso-date="2017-12-31"></transaction-date>
   <value currency="USD" value-date="2017-12-31">0.93</value>
   <description>
    <narrative xml:lang="EN">5.1 Project Coordination BIT</narrative>
   </description>
   <recipient-country code="CI"></recipient-country>
  </transaction>
  <transaction ref="102002-1-51-01-2017-4">
   <transaction-type code="4"></transaction-type>
   <transaction-date iso-date="2017-12-31"></transaction-date>
   <value currency="USD" value-date="2017-12-31">-4.35</value>
   <description>
    <narrative xml:lang="EN">5.1 Project Coordination BIT</narrative>
   </description>
   <recipient-country code="CI"></recipient-country>
  </transaction>
  <transaction ref="102002-1-51-01-2018-1">
   <transaction-type code="1"></transaction-type>
   <transaction-date iso-date="2018-12-31"></transaction-date>
   <value currency="USD" value-date="2018-12-31">-81.34</value>
   <description>
    <narrative xml:lang="EN">5.1 Project Coordination BIT</narrative>
   </description>
   <recipient-country code="CI"></recipient-country>
  </transaction>
  <transaction ref="102002-1-51-01-2018-4">
   <transaction-type code="4"></transaction-type>
   <transaction-date iso-date="2018-12-31"></transaction-date>
   <value currency="USD" value-date="2018-12-31">-75.14</value>
   <description>
    <narrative xml:lang="EN">5.1 Project Coordination BIT</narrative>
   </description>
   <recipient-country code="CI"></recipient-country>
  </transaction>
  <transaction ref="102002-1-51-02-2013-1">
   <transaction-type code="1"></transaction-type>
   <transaction-date iso-date="2013-12-31"></transaction-date>
   <value currency="USD" value-date="2013-12-31">6609.48</value>
   <description>
    <narrative xml:lang="EN">5.2 Project Coordination TCB</narrative>
   </description>
   <recipient-country code="CI"></recipient-country>
  </transaction>
  <transaction ref="102002-1-51-02-2013-4">
   <transaction-type code="4"></transaction-type>
   <transaction-date iso-date="2013-12-31"></transaction-date>
   <value currency="USD" value-date="2013-12-31">6871.38</value>
   <description>
    <narrative xml:lang="EN">5.2 Project Coordination TCB</narrative>
   </description>
   <recipient-country code="CI"></recipient-country>
  </transaction>
  <transaction ref="102002-1-51-02-2014-1">
   <transaction-type code="1"></transaction-type>
   <transaction-date iso-date="2014-12-31"></transaction-date>
   <value currency="USD" value-date="2014-12-31">51395.12</value>
   <description>
    <narrative xml:lang="EN">5.2 Project Coordination TCB</narrative>
   </description>
   <recipient-country code="CI"></recipient-country>
  </transaction>
  <transaction ref="102002-1-51-02-2014-4">
   <transaction-type code="4"></transaction-type>
   <transaction-date iso-date="2014-12-31"></transaction-date>
   <value currency="USD" value-date="2014-12-31">49003.59</value>
   <description>
    <narrative xml:lang="EN">5.2 Project Coordination TCB</narrative>
   </description>
   <recipient-country code="CI"></recipient-country>
  </transaction>
  <transaction ref="102002-1-51-02-2015-1">
   <transaction-type code="1"></transaction-type>
   <transaction-date iso-date="2015-12-31"></transaction-date>
   <value currency="USD" value-date="2015-12-31">6270.53</value>
   <description>
    <narrative xml:lang="EN">5.2 Project Coordination TCB</narrative>
   </description>
   <recipient-country code="CI"></recipient-country>
  </transaction>
  <transaction ref="102002-1-51-02-2015-4">
   <transaction-type code="4"></transaction-type>
   <transaction-date iso-date="2015-12-31"></transaction-date>
   <value currency="USD" value-date="2015-12-31">5733.44</value>
   <description>
    <narrative xml:lang="EN">5.2 Project Coordination TCB</narrative>
   </description>
   <recipient-country code="CI"></recipient-country>
  </transaction>
  <transaction ref="102002-1-51-03-2014-1">
   <transaction-type code="1"></transaction-type>
   <transaction-date iso-date="2014-12-31"></transaction-date>
   <value currency="USD" value-date="2014-12-31">39582.93</value>
   <description>
    <narrative xml:lang="EN">5.3 Evaluation</narrative>
   </description>
   <recipient-country code="CI"></recipient-country>
  </transaction>
  <transaction ref="102002-1-51-03-2014-4">
   <transaction-type code="4"></transaction-type>
   <transaction-date iso-date="2014-12-31"></transaction-date>
   <value currency="USD" value-date="2014-12-31">37922.13</value>
   <description>
    <narrative xml:lang="EN">5.3 Evaluation</narrative>
   </description>
   <recipient-country code="CI"></recipient-country>
  </transaction>
  <transaction ref="102002-1-51-03-2015-1">
   <transaction-type code="1"></transaction-type>
   <transaction-date iso-date="2015-12-31"></transaction-date>
   <value currency="USD" value-date="2015-12-31">1929.55</value>
   <description>
    <narrative xml:lang="EN">5.3 Evaluation</narrative>
   </description>
   <recipient-country code="CI"></recipient-country>
  </transaction>
  <transaction ref="102002-1-51-03-2015-4">
   <transaction-type code="4"></transaction-type>
   <transaction-date iso-date="2015-12-31"></transaction-date>
   <value currency="USD" value-date="2015-12-31">-1407.96</value>
   <description>
    <narrative xml:lang="EN">5.3 Evaluation</narrative>
   </description>
   <recipient-country code="CI"></recipient-country>
  </transaction>
  <transaction ref="102002-1-01-01-2013-1">
   <transaction-type code="1"></transaction-type>
   <transaction-date iso-date="2013-12-31"></transaction-date>
   <value currency="USD" value-date="2013-12-31">5001.01</value>
   <description>
    <narrative xml:lang="EN">EEIVC10001</narrative>
   </description>
   <recipient-country code="CI"></recipient-country>
  </transaction>
  <transaction ref="102002-1-01-01-2013-4">
   <transaction-type code="4"></transaction-type>
   <transaction-date iso-date="2013-12-31"></transaction-date>
   <value currency="USD" value-date="2013-12-31">4312.76</value>
   <description>
    <narrative xml:lang="EN">EEIVC10001</narrative>
   </description>
   <recipient-country code="CI"></recipient-country>
  </transaction>
  <transaction ref="102002-1-01-01-2014-1">
   <transaction-type code="1"></transaction-type>
   <transaction-date iso-date="2014-12-31"></transaction-date>
   <value currency="USD" value-date="2014-12-31">-7408.14</value>
   <description>
    <narrative xml:lang="EN">EEIVC10001</narrative>
   </description>
   <recipient-country code="CI"></recipient-country>
  </transaction>
  <transaction ref="102002-1-01-01-2014-4">
   <transaction-type code="4"></transaction-type>
   <transaction-date iso-date="2014-12-31"></transaction-date>
   <value currency="USD" value-date="2014-12-31">-7295.51</value>
   <description>
    <narrative xml:lang="EN">EEIVC10001</narrative>
   </description>
   <recipient-country code="CI"></recipient-country>
  </transaction>
  <transaction ref="102002-1-01-01-2015-1">
   <transaction-type code="1"></transaction-type>
   <transaction-date iso-date="2015-12-31"></transaction-date>
   <value currency="USD" value-date="2015-12-31">-754.07</value>
   <description>
    <narrative xml:lang="EN">EEIVC10001</narrative>
   </description>
   <recipient-country code="CI"></recipient-country>
  </transaction>
  <transaction ref="102002-1-01-01-2015-4">
   <transaction-type code="4"></transaction-type>
   <transaction-date iso-date="2015-12-31"></transaction-date>
   <value currency="USD" value-date="2015-12-31">-1415.88</value>
   <description>
    <narrative xml:lang="EN">EEIVC10001</narrative>
   </description>
   <recipient-country code="CI"></recipient-country>
  </transaction>
  <transaction ref="102002-1-01-02-2013-1">
   <transaction-type code="1"></transaction-type>
   <transaction-date iso-date="2013-12-31"></transaction-date>
   <value currency="USD" value-date="2013-12-31">9063</value>
   <description>
    <narrative xml:lang="EN">EEIVC10A01</narrative>
   </description>
   <recipient-country code="CI"></recipient-country>
  </transaction>
  <transaction ref="102002-1-01-02-2013-4">
   <transaction-type code="4"></transaction-type>
   <transaction-date iso-date="2013-12-31"></transaction-date>
   <value currency="USD" value-date="2013-12-31">8951.97</value>
   <description>
    <narrative xml:lang="EN">EEIVC10A01</narrative>
   </description>
   <recipient-country code="CI"></recipient-country>
  </transaction>
 </iati-activity>
</iati-activities>
